flask_gae_users/__init__.py
flask_gae_users/flaskgaeusers.py
flask_gae_users-0.0.1.dist-info/METADATA
flask_gae_users-0.0.1.dist-info/RECORD
flask_gae_users-0.0.1.dist-info/WHEEL
flask_gae_users-0.0.1.dist-info/top_level.txt
