Metadata-Version: 2.1
Name: flask-gae-users
Version: 0.0.1
Summary: Provide route decorators for Google App Engine users
Home-page: https://gitlab.com/vector.kerr/flask-gae-users
Author: Daniel 'Vector' Kerr
Author-email: vector@vector.id.au
License: MIT
Keywords: flask google app engine gae user users decorator
Platform: UNKNOWN
Classifier: Programming Language :: Python :: 2
Classifier: License :: OSI Approved :: MIT License
Classifier: Operating System :: OS Independent
Requires-Dist: flask
